bcdtogray/bcdtogray.v
module bcdtogray(g3,g2,g1,g0,b3,b2,b1,b0);
output g3,g2,g1,g0;
input b3,b2,b1,b0;
assign g3=b3;
assign g2=b2^b3;
assign g1=b1^b2;
assign g0=b0^b1;
endmodule

bcdtogray/bcdtogray_tb.v
`include "bcdtogray.v"
module bcdtogray_tb();
reg b3,b2,b1,b0;
wire g3,g2,g1,g0;
bcdtogray b1g1(g3,g2,g1,g0,b3,b2,b1,b0);
initial begin
    $dumpfile("dump.vcd");
    $dumpvars(1);
    b3=0;
    b2=0;
    b1=0;
    b0=0;
    #1
    b3=0;
    b2=0;
    b1=0;
    b0=1;
    #1
    b3=0;
    b2=0;
    b1=1;
    b0=0;
    #1
    b3=0;
    b2=0;
    b1=1;
    b0=1;
    #1
    b3=0;
    b2=1;
    b1=0;
    b0=0;
    #1
    b3=0;
    b2=1;
    b1=0;
    b0=1;
    #1
    b3=0;
    b2=1;
    b1=1;
    b0=0;
    #1
    b3=0;
    b2=1;
    b1=1;
    b0=1;
    #1
    b3=1;
    b2=0;
    b1=0;
    b0=0;
    #1
    b3=1;
    b2=0;
    b1=0;
    b0=1;
    #1
    $finish;
end
endmodule

bcdtogray/dump.vcd
$date
	Sun Jan 29 19:01:52 2023
$end
$version
	Icarus Verilog
$end
$timescale
	1s
$end
$scope module bcdtogray_tb $end
$var wire 1 ! g3 $end
$var wire 1 " g2 $end
$var wire 1 # g1 $end
$var wire 1 $ g0 $end
$var reg 1 % b0 $end
$var reg 1 & b1 $end
$var reg 1 ' b2 $end
$var reg 1 ( b3 $end
$upscope $end
$enddefinitions $end
$comment Show the parameter values. $end
$dumpall
$end
#0
$dumpvars
0(
0'
0&
0%
0$
0#
0"
0!
$end
#1
1$
1%
#2
1#
0%
1&
#3
0$
1%
#4
1"
0%
0&
1'
#5
1$
1%
#6
0#
0%
1&
#7
0$
1%
#8
0%
0&
0'
1!
1(
#9
1$
1%
